boto3_helpers/__init__.py
boto3_helpers/arn.py
boto3_helpers/awslambda.py
boto3_helpers/cloudwatch.py
boto3_helpers/dynamodb.py
boto3_helpers/events.py
boto3_helpers/kinesis.py
boto3_helpers/medialive.py
boto3_helpers/mediatailor.py
boto3_helpers/pagination.py
boto3_helpers/s3.py
boto3_helpers/signed_requests.py
boto3_helpers/sqs.py
boto3_helpers/sts.py
boto3_helpers-2.5.0.dist-info/LICENSE
boto3_helpers-2.5.0.dist-info/METADATA
boto3_helpers-2.5.0.dist-info/WHEEL
boto3_helpers-2.5.0.dist-info/top_level.txt
boto3_helpers-2.5.0.dist-info/RECORD
