Metadata-Version: 2.1
Name: boto3-helpers
Version: 2.5.0
Summary: Helper utilities for boto3
Author: Bo Bayles
Author-email: bo.bayles@wurl.com
License: Apache 2.0
Project-URL: homepage, https://github.com/openwurl/boto3-helpers
Classifier: License :: OSI Approved :: Apache Software License
Classifier: Programming Language :: Python :: 3
Classifier: Programming Language :: Python :: 3 :: Only
Requires-Python: >=3.8
License-File: LICENSE
Requires-Dist: boto3
Requires-Dist: botocore
